Workbook
Name aporte: Principal!$D$10:$D$10
Name dividendos: Principal!$D$14:$D$14
Name patrimonio: Principal!$D$13:$D$13
Name qtd_anos: Principal!$D$11:$D$11
Name rendimento_carteira: Principal!$D$6:$D$6
Name salario: Principal!$D$5:$D$5
Name sugestao_investimento: Principal!$D$7:$D$7
Name taxa_mensal: Principal!$D$12:$D$12

Sheet Principal
B4: Configurações
B5: Salário | D5: 3500
B6: Rendimento carteira | D6: 0.0089
B7: Sugestão Investimento (30%) | D7: {=salario*30%} -> 1050
B9: Investimento Mensal
B10: Quanto investir por mês? | D10: 100
B11: Por quantos anos? | D11: 3
B12: Taxa de rendimento mensal? | D12: 0.01079
B13: Patrimônio acumulado? | D13: {=FV(taxa_mensal,qtd_anos*12,aporte*-1)} -> 4370.8374
B14: Dividendos mensais? | D14: {=patrimonio*rendimento_carteira} -> 38.900453
B16: Cenários | D16: Dividendos
A17: 2 | B17: Quanto em 2 anos? | C17: {=FV(taxa_mensal,$A17*12,aporte*-1)} -> 2722.7627 | D17: {=C17*rendimento_carteira} -> 24.232588
A18: 5 | B18: Quanto em 5 anos? | C18: {=FV(taxa_mensal,$A18*12,aporte*-1)} -> 8377.6914 | D18: {=C18*rendimento_carteira} -> 74.561453
A19: 10 | B19: Quanto em 10 anos? | C19: {=FV(taxa_mensal,$A19*12,aporte*-1)} -> 24328.421 | D19: {=C19*rendimento_carteira} -> 216.52295
A20: 20 | B20: Quanto em 20 anos? | C20: {=FV(taxa_mensal,$A20*12,aporte*-1)} -> 112519.84 | D20: {=C20*rendimento_carteira} -> 1001.4266
A21: 30 | B21: Quanto em 30 anos? | C21: {=FV(taxa_mensal,$A21*12,aporte*-1)} -> 432216.97 | D21: {=C21*rendimento_carteira} -> 3846.731
B23: Perfil | D23: Conservador
B24: Valor a ser investido por mês | D24: {=aporte} -> 100
B26: Tipo de FII | C26: Percentual sugerido | D26: Valores
B27: Papel | C27: =VLOOKUP($D$23&"-"&B27,Apoio!$A:$D,4,FALSE) -> 0.3 | D27: =C27*$D$24 -> 30
B28: Tijolo | C28: =VLOOKUP($D$23&"-"&B28,Apoio!$A:$D,4,FALSE) -> 0.5 | D28: =C28*$D$24 -> 50
B29: Híbridos | C29: =VLOOKUP($D$23&"-"&B29,Apoio!$A:$D,4,FALSE) -> 0.1 | D29: =C29*$D$24 -> 10
B30: FOFs | C30: =VLOOKUP($D$23&"-"&B30,Apoio!$A:$D,4,FALSE) -> 0.1 | D30: =C30*$D$24 -> 10
B31: Desenvolvimento | C31: =VLOOKUP($D$23&"-"&B31,Apoio!$A:$D,4,FALSE) -> 0 | D31: =C31*$D$24 -> 0
B32: Hotelaria | C32: =VLOOKUP($D$23&"-"&B32,Apoio!$A:$D,4,FALSE) -> 0 | D32: =C32*$D$24 -> 0
B33: Soma | D33: =SUM(D27:D32) -> 100

Sheet Apoio
A2: Chave | B2: Perfil | C2: Tipo de FII | D2: %
A3: =Apoio!B3&"-"&Apoio!C3 -> Conservador-Papel | B3: Conservador | C3: Papel | D3: 0.3
A4: =Apoio!B4&"-"&Apoio!C4 -> Conservador-Tijolo | B4: Conservador | C4: Tijolo | D4: 0.5
A5: =Apoio!B5&"-"&Apoio!C5 -> Conservador-Híbridos | B5: Conservador | C5: Híbridos | D5: 0.1
A6: =Apoio!B6&"-"&Apoio!C6 -> Conservador-FOFs | B6: Conservador | C6: FOFs | D6: 0.1
A7: =Apoio!B7&"-"&Apoio!C7 -> Conservador-Desenvolvimento | B7: Conservador | C7: Desenvolvimento | D7: 0
A8: =Apoio!B8&"-"&Apoio!C8 -> Conservador-Hotelaria | B8: Conservador | C8: Hotelaria | D8: 0
A9: =B9&"-"&C9 -> Moderado-Papel | B9: Moderado | C9: Papel | D9: 0.32
A10: =B10&"-"&C10 -> Moderado-Tijolo | B10: Moderado | C10: Tijolo | D10: 0.35
A11: =B11&"-"&C11 -> Moderado-Híbridos | B11: Moderado | C11: Híbridos | D11: 0.08
A12: =B12&"-"&C12 -> Moderado-FOFs | B12: Moderado | C12: FOFs | D12: 0.05
A13: =B13&"-"&C13 -> Moderado-Desenvolvimento | B13: Moderado | C13: Desenvolvimento | D13: 0.1
A14: =B14&"-"&C14 -> Moderado-Hotelaria | B14: Moderado | C14: Hotelaria | D14: 0.1
A15: =B15&"-"&C15 -> Agressivo-Papel | B15: Agressivo | C15: Papel | D15: 0.5
A16: =B16&"-"&C16 -> Agressivo-Tijolo | B16: Agressivo | C16: Tijolo | D16: 0.1
A17: =B17&"-"&C17 -> Agressivo-Híbridos | B17: Agressivo | C17: Híbridos | D17: 0.05
A18: =B18&"-"&C18 -> Agressivo-FOFs | B18: Agressivo | C18: FOFs | D18: 0.05
A19: =B19&"-"&C19 -> Agressivo-Desenvolvimento | B19: Agressivo | C19: Desenvolvimento | D19: 0.2
A20: =B20&"-"&C20 -> Agressivo-Hotelaria | B20: Agressivo | C20: Hotelaria | D20: 0.1
